ep_bandpass_filter_selector/__init__.py
ep_bandpass_filter_selector/selector.py
ep_bandpass_filter_selector-0.2.0.dist-info/LICENSE
ep_bandpass_filter_selector-0.2.0.dist-info/METADATA
ep_bandpass_filter_selector-0.2.0.dist-info/WHEEL
ep_bandpass_filter_selector-0.2.0.dist-info/RECORD
