Metadata-Version: 2.1
Name: ep-bandpass-filter-selector
Version: 0.2.0
Summary: 
Author: Yaricp Pisarev
Author-email: yaricp@gmail.com
Requires-Python: >=3.6.9,<4.0.0
Classifier: Programming Language :: Python :: 3
Classifier: Programming Language :: Python :: 3.7
Classifier: Programming Language :: Python :: 3.8
Classifier: Programming Language :: Python :: 3.9
Classifier: Programming Language :: Python :: 3.10
Classifier: Programming Language :: Python :: 3.11
Classifier: Programming Language :: Python :: 3.12
Requires-Dist: eeg-filters (>=0.0.7,<0.0.8)
Requires-Dist: loguru (>=0.7.2,<0.8.0)
Requires-Dist: numpy (>=1.26.3,<2.0.0)
